biopb/image/__init__.py
biopb/image/bindata_pb2.py
biopb/image/bindata_pb2_grpc.py
biopb/image/detection_request_pb2.py
biopb/image/detection_request_pb2_grpc.py
biopb/image/detection_response_pb2.py
biopb/image/detection_response_pb2_grpc.py
biopb/image/detection_settings_pb2.py
biopb/image/detection_settings_pb2_grpc.py
biopb/image/image_data_pb2.py
biopb/image/image_data_pb2_grpc.py
biopb/image/roi_pb2.py
biopb/image/roi_pb2_grpc.py
biopb/image/rpc_object_detection_pb2.py
biopb/image/rpc_object_detection_pb2_grpc.py
biopb/image/rpc_process_image_pb2.py
biopb/image/rpc_process_image_pb2_grpc.py
biopb/image/utils.py
biopb/ome/annotation_pb2.py
biopb/ome/annotation_pb2_grpc.py
biopb/ome/bindata_pb2.py
biopb/ome/bindata_pb2_grpc.py
biopb/ome/dataset_pb2.py
biopb/ome/dataset_pb2_grpc.py
biopb/ome/detector_pb2.py
biopb/ome/detector_pb2_grpc.py
biopb/ome/detector_setting_pb2.py
biopb/ome/detector_setting_pb2_grpc.py
biopb/ome/experiment_pb2.py
biopb/ome/experiment_pb2_grpc.py
biopb/ome/experimenter_group_pb2.py
biopb/ome/experimenter_group_pb2_grpc.py
biopb/ome/experimenter_pb2.py
biopb/ome/experimenter_pb2_grpc.py
biopb/ome/filter_pb2.py
biopb/ome/filter_pb2_grpc.py
biopb/ome/filter_set_pb2.py
biopb/ome/filter_set_pb2_grpc.py
biopb/ome/folder_pb2.py
biopb/ome/folder_pb2_grpc.py
biopb/ome/image_pb2.py
biopb/ome/image_pb2_grpc.py
biopb/ome/instrument_pb2.py
biopb/ome/instrument_pb2_grpc.py
biopb/ome/light_source_pb2.py
biopb/ome/light_source_pb2_grpc.py
biopb/ome/light_source_setting_pb2.py
biopb/ome/light_source_setting_pb2_grpc.py
biopb/ome/lightpath_pb2.py
biopb/ome/lightpath_pb2_grpc.py
biopb/ome/manufacturer_spec_pb2.py
biopb/ome/manufacturer_spec_pb2_grpc.py
biopb/ome/metadata_pb2.py
biopb/ome/metadata_pb2_grpc.py
biopb/ome/metadata_ref_pb2.py
biopb/ome/metadata_ref_pb2_grpc.py
biopb/ome/microbeam_manipulation_pb2.py
biopb/ome/microbeam_manipulation_pb2_grpc.py
biopb/ome/microscope_pb2.py
biopb/ome/microscope_pb2_grpc.py
biopb/ome/objective_pb2.py
biopb-0.1.4.dist-info/licenses/LICENSE
biopb-0.1.4.dist-info/METADATA
biopb-0.1.4.dist-info/WHEEL
biopb-0.1.4.dist-info/top_level.txt
biopb-0.1.4.dist-info/RECORD
