Metadata-Version: 2.4
Name: biopb
Version: 0.1.4
Summary: Python bindings of BioPB: open protobuf/gRPC protocols for biomedical image processing
Author-email: Ji Yu <jyu@uchc.edu>
License-Expression: MIT
Project-URL: Homepage, https://github.com/biopb/biopb
Requires-Python: >=3.8
License-File: LICENSE
Requires-Dist: protobuf>=6.32.1
Requires-Dist: grpcio
Requires-Dist: numpy
Provides-Extra: test
Requires-Dist: pytest<8,>=7.0; extra == "test"
Dynamic: license-file
